CHANGELOG.md
LICENSE
MANIFEST.in
README.md
midware.py
setup.cfg
setup.py
midware.egg-info/PKG-INFO
midware.egg-info/SOURCES.txt
midware.egg-info/dependency_links.txt
midware.egg-info/top_level.txt