Metadata-Version: 1.1
Name: midware
Version: 0.5.1
Summary: A simple general-purpose middleware library for Python
Home-page: https://github.com/idmit/midware
Author: Ivan Dmitrievsky
Author-email: ivan.dmitrievsky+python@gmail.com
License: MIT License
